surfgram/__init__.py
surfgram/core/__init__.py
surfgram/core/bot/__init__.py
surfgram/core/fsm/__init__.py
surfgram/core/fsm/meta.py
surfgram/core/fsm/state.py
surfgram/core/fsm/states.py
surfgram/core/fsm/storage/__init__.py
surfgram/core/fsm/storage/base.py
surfgram/core/fsm/storage/in_memory.py
surfgram/core/fsm/storage/redis.py
surfgram/core/helpers/__init__.py
surfgram/core/helpers/converters/__init__.py
surfgram/core/helpers/converters/camel_case_converter.py
surfgram/core/helpers/converters/converter.py
surfgram/core/helpers/converters/snake_case_converter.py
surfgram/core/helpers/link.py
surfgram/core/helpers/markup/__init__.py
surfgram/core/helpers/markup/html.py
surfgram/core/helpers/markup/markdown.py
surfgram/core/listeners/__init__.py
surfgram/core/listeners/base_listener.py
surfgram/core/listeners/listener.py
surfgram/core/structures/__init__.py
surfgram/core/structures/api_object.py
surfgram/core/structures/configs.py
surfgram/core/validator/__init__.py
surfgram/core/validator/token.py
surfgram/exceptions/__init__.py
surfgram/exceptions/bot_exception.py
surfgram/exceptions/token_exception.py
surfgram/types/__init__.py
surfgram/types/accepted_gift_types/__init__.py
surfgram/types/accepted_gift_types/accepted_gift_types.py
surfgram/types/accepted_gift_types/factory.py
surfgram/types/affiliate_info/__init__.py
surfgram/types/affiliate_info/affiliate_info.py
surfgram/types/affiliate_info/factory.py
surfgram/types/animation/__init__.py
surfgram/types/animation/animation.py
surfgram/types/animation/factory.py
surfgram/types/audio/__init__.py
surfgram/types/audio/audio.py
surfgram/types/audio/factory.py
surfgram/types/background_fill_freeform_gradient/__init__.py
surfgram/types/background_fill_freeform_gradient/background_fill_freeform_gradient.py
surfgram/types/background_fill_freeform_gradient/factory.py
surfgram/types/background_fill_gradient/__init__.py
surfgram/types/background_fill_gradient/background_fill_gradient.py
surfgram-1.0.1.dist-info/entry_points.txt
surfgram-1.0.1.dist-info/LICENSE
surfgram-1.0.1.dist-info/METADATA
surfgram-1.0.1.dist-info/WHEEL
surfgram-1.0.1.dist-info/RECORD
