Metadata-Version: 2.3
Name: surfgram
Version: 1.0.1
Summary: Modern asynchronous Telegram bot framework
License: MIT
Keywords: telegram,bot,framework,async,aiohttp,telegram-api,python-telegram-bot
Author: anybody
Author-email: help.surfgram@gmail.com
Requires-Python: >=3.9,<4.0
Classifier: Development Status :: 5 - Production/Stable
Classifier: Intended Audience :: Developers
Classifier: License :: OSI Approved :: MIT License
Classifier: Programming Language :: Python :: 3
Classifier: Programming Language :: Python :: 3.9
Classifier: Programming Language :: Python :: 3.10
Classifier: Programming Language :: Python :: 3.11
Classifier: Programming Language :: Python :: 3.12
Classifier: Programming Language :: Python :: 3.13
Classifier: Topic :: Communications :: Chat
Classifier: Topic :: Software Development :: Libraries :: Application Frameworks
Classifier: Typing :: Typed
Provides-Extra: uvloop
Requires-Dist: surfgram_cli (>=1.0.1,<2.0.0)
Requires-Dist: surfgram_internal (==0.2)
Requires-Dist: uvloop (>=0.18.0,<0.19.0) ; extra == "uvloop"
Project-URL: Bug Tracker, https://github.com/surfgram/surfgram/issues
Project-URL: Changelog, https://github.com/surfgram/surfgram/releases
Project-URL: Documentation, https://github.com/surfgram/surfgram-docs
Project-URL: Homepage, https://github.com/surfgram/surfgram
Project-URL: Repository, https://github.com/surfgram/surfgram
